MANIFEST.in
README.md
README.txt
setup.py
icinga2api/__init__.py
icinga2api/actions.py
icinga2api/base.py
icinga2api/client.py
icinga2api/configfile.py
icinga2api/events.py
icinga2api/exceptions.py
icinga2api/objects.py
icinga2api/status.py
icinga2api.egg-info/PKG-INFO
icinga2api.egg-info/SOURCES.txt
icinga2api.egg-info/dependency_links.txt
icinga2api.egg-info/not-zip-safe
icinga2api.egg-info/requires.txt
icinga2api.egg-info/top_level.txt